{"assets":{"C02892334FA92342460F800E19D89680":{"type":"texture","index":1054,"assetRequest":{"type":"slide","state":"contents","slide":"18616DEE-7FFF-4FD0-97FA-6F516B944C1E"},"url":"assets/C02892334FA92342460F800E19D89680.svg","width":868,"height":68},"C432C237D75414711234682F59B0DA1C":{"type":"texture","index":1056,"assetRequest":{"type":"slide","state":"contents","slide":"18616DEE-7FFF-4FD0-97FA-6F516B944C1E"},"url":"assets/C432C237D75414711234682F59B0DA1C.svg","width":1924,"height":1082},"B5B667008212B1F34D2070F84C2B1478":{"type":"texture","index":1055,"assetRequest":{"type":"slide","state":"contents","slide":"18616DEE-7FFF-4FD0-97FA-6F516B944C1E"},"url":"assets/B5B667008212B1F34D2070F84C2B1478.svg","width":820,"height":32},"E8E583B01A0E2BC12C84C0EBFCE59203":{"type":"texture","index":1051,"assetRequest":{"type":"slide","state":"contents","slide":"18616DEE-7FFF-4FD0-97FA-6F516B944C1E"},"url":"assets/E8E583B01A0E2BC12C84C0EBFCE59203.svg","width":1924,"height":1086},"27A1459428E2114F8A04E93134B69D52":{"type":"texture","index":1053,"assetRequest":{"type":"slide","state":"contents","slide":"18616DEE-7FFF-4FD0-97FA-6F516B944C1E"},"url":"assets/27A1459428E2114F8A04E93134B69D52.svg","width":37,"height":36},"C7B5ACFCFF92ABC36D7C749C7A2B6515":{"type":"texture","index":1052,"assetRequest":{"type":"slide","state":"contents","slide":"18616DEE-7FFF-4FD0-97FA-6F516B944C1E"},"url":"assets/C7B5ACFCFF92ABC36D7C749C7A2B6515.svg","width":421,"height":391},"4DEFF49A7D65120150224652EBA0FF43":{"type":"texture","index":1058,"assetRequest":{"type":"slide","state":"incoming","slide":"447905A3-5095-414C-B4DC-C61AAB02D68F"},"url":"assets/4DEFF49A7D65120150224652EBA0FF43.svg","width":1920,"height":1080},"0625B09B9D2280932346BEB487E34EC5":{"type":"texture","index":1050,"assetRequest":{"type":"slide","state":"contents","slide":"18616DEE-7FFF-4FD0-97FA-6F516B944C1E"},"url":"assets/0625B09B9D2280932346BEB487E34EC5.svg","width":1920,"height":1080},"9FD2022F37B1D3211486583890BCABA4":{"type":"texture","index":1057,"assetRequest":{"type":"slide","state":"outgoing","slide":"18616DEE-7FFF-4FD0-97FA-6F516B944C1E"},"url":"assets/9FD2022F37B1D3211486583890BCABA4.svg","width":1920,"height":1080}},"events":[{"effects":[{"beginTime":0.1,"baseLayer":{"animations":[],"initialState":{"affineTransform":[1,0,0,1,0,0],"masksToBounds":false,"rotation":0,"scale":1,"position":{"pointX":959.9999933242798,"pointY":138.102383852005},"width":881.7304612733424,"sublayerTransform":[1,0,0,0,0,1,0,0,0,0,1,0,0,0,0,1],"contentsRect":{"y":0,"x":0,"width":1,"height":1},"opacity":1,"edgeAntialiasingMask":15,"height":109.0000025267909,"hidden":false,"anchorPoint":{"pointX":0.5,"pointY":0.5}},"objectID":"BDFF1EE7-2C52-439F-AE45-28420255D6E5","layers":[{"animations":[],"initialState":{"affineTransform":[1,0,0,1,0,0],"masksToBounds":false,"rotation":0,"scale":1,"position":{"pointX":440.8652373123914,"pointY":456.3976174113905},"width":881.7304612733424,"sublayerTransform":[1,0,0,0,0,1,0,0,0,0,1,-0.0003500791246677598,0,0,0,1],"contentsRect":{"y":0,"x":0,"width":1,"height":1},"opacity":1,"edgeAntialiasingMask":15,"height":109.0000025267909,"hidden":false,"anchorPoint":{"pointX":0.5000000075711575,"pointY":4.187134007627323}},"layers":[{"animations":[{"repeatCount":0,"animations":[{"timingFunctions":[{"timingFunction":"custom","timingControlPoint1y":0.4998149275779724,"timingControlPoint2x":0.6016100645065308,"timingControlPoint1x":0.4063220918178558,"timingControlPoint2y":1}],"values":[{"pointX":-962.9999866485596,"pointY":55.39761741139046},{"pointX":439.8652373123914,"pointY":55.39761741139046}],"beginTime":0,"repeatCount":0,"keyTimes":[0,1],"property":"position","fillMode":"both","duration":0.8},{"from":{"scalar":false},"beginTime":0,"repeatCount":0,"fillMode":"forwards","property":"hidden","duration":0.8,"to":{"scalar":false}}],"beginTime":0.1,"fillMode":"both","duration":0.8}],"layers":[],"initialState":{"affineTransform":[1,0,0,1,0,0],"masksToBounds":false,"rotation":0,"scale":1,"position":{"pointX":439.8652373123914,"pointY":55.39761741139046},"width":868,"sublayerTransform":[1,0,0,0,0,1,0,0,0,0,1,0,0,0,0,1],"contentsRect":{"y":0,"x":0,"width":1,"height":1},"opacity":1,"edgeAntialiasingMask":0,"height":68,"hidden":true,"anchorPoint":{"pointX":0.5,"pointY":0.5}},"texture":"C02892334FA92342460F800E19D89680"}]}]},"effects":[],"duration":0.8,"type":"buildIn","name":"apple:move in character","objectID":"BDFF1EE7-2C52-439F-AE45-28420255D6E5"},{"beginTime":0.2,"baseLayer":{"animations":[],"initialState":{"affineTransform":[1,0,0,1,0,0],"masksToBounds":false,"rotation":0,"scale":1,"position":{"pointX":960,"pointY":220.1779934167862},"width":982.9769897460938,"sublayerTransform":[1,0,0,0,0,1,0,0,0,0,1,0,0,0,0,1],"contentsRect":{"y":0,"x":0,"width":1,"height":1},"opacity":1,"edgeAntialiasingMask":15,"height":44.00000047683716,"hidden":false,"anchorPoint":{"pointX":0.5,"pointY":0.5}},"objectID":"94CC132C-DEC5-4D1A-882C-F54DBE7A5475","layers":[{"animations":[],"initialState":{"affineTransform":[1,0,0,1,0,0],"masksToBounds":false,"rotation":0,"scale":1,"position":{"pointX":491.4884948730469,"pointY":341.8220068216324},"width":982.9769897460938,"sublayerTransform":[1,0,0,0,0,1,0,0,0,0,1,-0.0003500791246677598,0,0,0,1],"contentsRect":{"y":0,"x":0,"width":1,"height":1},"opacity":1,"edgeAntialiasingMask":15,"height":44.00000047683716,"hidden":false,"anchorPoint":{"pointX":0.5,"pointY":7.768681889028096}},"layers":[{"animations":[{"repeatCount":0,"animations":[{"timingFunctions":[{"timingFunction":"custom","timingControlPoint1y":0.4998149275779724,"timingControlPoint2x":0.6016100645065308,"timingControlPoint1x":0.4063220918178558,"timingControlPoint2y":1}],"values":[{"pointX":1944.976989746094,"pointY":25.82200682163239},{"pointX":491.4884948730469,"pointY":25.82200682163239}],"beginTime":0,"repeatCount":0,"keyTimes":[0,1],"property":"position","fillMode":"both","duration":0.8},{"from":{"scalar":false},"beginTime":0,"repeatCount":0,"fillMode":"forwards","property":"hidden","duration":0.8,"to":{"scalar":false}}],"beginTime":0.2,"fillMode":"both","duration":0.8}],"layers":[],"initialState":{"affineTransform":[1,0,0,1,0,0],"masksToBounds":false,"rotation":0,"scale":1,"position":{"pointX":491.4884948730469,"pointY":25.82200682163239},"width":820,"sublayerTransform":[1,0,0,0,0,1,0,0,0,0,1,0,0,0,0,1],"contentsRect":{"y":0,"x":0,"width":1,"height":1},"opacity":1,"edgeAntialiasingMask":0,"height":32,"hidden":true,"anchorPoint":{"pointX":0.5,"pointY":0.5}},"texture":"B5B667008212B1F34D2070F84C2B1478"}]}]},"effects":[],"duration":0.8,"type":"buildIn","name":"apple:move in character","objectID":"94CC132C-DEC5-4D1A-882C-F54DBE7A5475"},{"beginTime":0.6000000000000001,"baseLayer":{"animations":[],"initialState":{"affineTransform":[1,0,0,1,0,0],"masksToBounds":false,"rotation":0,"scale":1,"position":{"pointX":959.9999923706055,"pointY":566.4665451049805},"width":509,"sublayerTransform":[1,0,0,0,0,1,0,0,0,0,1,0,0,0,0,1],"contentsRect":{"y":0,"x":0,"width":1,"height":1},"opacity":1,"edgeAntialiasingMask":15,"height":559,"hidden":false,"anchorPoint":{"pointX":0.5,"pointY":0.5}},"objectID":"36744CC5-8A06-40CA-9654-ED4CA37E5193","layers":[{"animations":[],"initialState":{"affineTransform":[1,0,0,1,0,0],"masksToBounds":false,"rotation":0,"scale":1,"position":{"pointX":254.5000076293945,"pointY":253.0334548950195},"width":509,"sublayerTransform":[1,0,0,0,0,1,0,0,0,0,1,-0.0003500791246677598,0,0,0,1],"contentsRect":{"y":0,"x":0,"width":1,"height":1},"opacity":1,"edgeAntialiasingMask":15,"height":559,"hidden":false,"anchorPoint":{"pointX":0.5000000149889873,"pointY":0.4526537654651512}},"layers":[{"animations":[{"repeatCount":0,"animations":[{"repeatCount":0,"timingControlPoint2y":1,"from":{"scalar":0},"timingFunction":"custom","timingControlPoint1x":0.4967894852161407,"property":"opacity","fillMode":"both","duration":1,"beginTime":0,"timingControlPoint2x":0.5012362599372864,"timingControlPoint1y":0.001364695723168552,"to":{"scalar":1}},{"from":{"scalar":-210.5},"beginTime":0,"repeatCount":0,"fillMode":"removed","property":"anchorPointZ","duration":1,"to":{"scalar":-210.5}},{"from":{"scalar":-210.5},"beginTime":0,"repeatCount":0,"fillMode":"removed","property":"zPosition","duration":1,"to":{"scalar":-210.5}},{"from":{"scalar":false},"beginTime":0,"repeatCount":0,"fillMode":"removed","property":"doubleSided","duration":1,"to":{"scalar":false}},{"from":{"scalar":false},"beginTime":0,"repeatCount":0,"fillMode":"both","property":"hidden","duration":1,"to":{"scalar":false}},{"repeatCount":0,"timingControlPoint2y":1,"from":{"scalar":-1.570796326794897},"timingFunction":"custom","timingControlPoint1x":0.4967894852161407,"property":"transform.rotation.y","fillMode":"removed","duration":1,"beginTime":0,"timingControlPoint2x":0.5012362599372864,"timingControlPoint1y":0.001364695723168552,"to":{"scalar":-0}}],"beginTime":0.6000000000000001,"fillMode":"both","duration":1}],"layers":[],"initialState":{"affineTransform":[1,0,0,1,0,0],"masksToBounds":false,"rotation":0,"scale":1,"position":{"pointX":254.0000076293945,"pointY":262.5334548950195},"width":421,"sublayerTransform":[1,0,0,0,0,1,0,0,0,0,1,0,0,0,0,1],"contentsRect":{"y":0,"x":0,"width":1,"height":1},"opacity":1,"edgeAntialiasingMask":0,"height":391,"hidden":true,"anchorPoint":{"pointX":0.5,"pointY":0.5}},"texture":"C7B5ACFCFF92ABC36D7C749C7A2B6515"}]}]},"effects":[],"duration":1,"type":"buildIn","name":"apple:bc-3D-cube","objectID":"36744CC5-8A06-40CA-9654-ED4CA37E5193"},{"beginTime":1,"baseLayer":{"animations":[],"initialState":{"affineTransform":[1,0,0,1,0,0],"masksToBounds":false,"rotation":0,"scale":1,"position":{"pointX":959.999999480588,"pointY":1024.898193478584},"width":47.57143020629883,"sublayerTransform":[1,0,0,0,0,1,0,0,0,0,1,0,0,0,0,1],"contentsRect":{"y":0,"x":0,"width":1,"height":1},"opacity":1,"edgeAntialiasingMask":15,"height":69,"hidden":false,"anchorPoint":{"pointX":0.5,"pointY":0.5}},"objectID":"C83C8740-CA88-47B1-854B-000395E53166","layers":[{"animations":[],"initialState":{"affineTransform":[1,0,0,1,0,0],"masksToBounds":false,"rotation":0,"scale":1,"position":{"pointX":23.78571562256138,"pointY":-450.3981934785843},"width":47.57143020629883,"sublayerTransform":[1,0,0,0,0,1,0,0,0,0,1,-0.0003500791246677598,0,0,0,1],"contentsRect":{"y":0,"x":0,"width":1,"height":1},"opacity":1,"edgeAntialiasingMask":15,"height":69,"hidden":false,"anchorPoint":{"pointX":0.5000000109185696,"pointY":-6.527510050414265}},"layers":[{"animations":[{"repeatCount":0,"animations":[{"repeatCount":0,"timingControlPoint2y":1,"from":{"scalar":-3.141592653589793},"timingFunction":"custom","timingControlPoint1x":0.3953104317188263,"property":"transform.rotation.y","fillMode":"removed","duration":0.9,"beginTime":0,"timingControlPoint2x":0.3992834389209747,"timingControlPoint1y":0.004784102085977793,"to":{"scalar":0}},{"timingFunctions":[{"timingFunction":"custom","timingControlPoint1y":0,"timingControlPoint2x":0.3796900808811188,"timingControlPoint1x":0.6810944080352783,"timingControlPoint2y":0.9981408715248108},{"timingFunction":"linear"}],"values":[{"scalar":0},{"scalar":1},{"scalar":1}],"beginTime":0,"repeatCount":0,"keyTimes":[0,0.9,1],"property":"opacity","fillMode":"both","duration":0.9},{"from":{"scalar":false},"beginTime":0.0001,"repeatCount":0,"fillMode":"forwards","property":"hidden","duration":0.8999,"to":{"scalar":false}}],"beginTime":1,"fillMode":"both","duration":0.9}],"layers":[],"initialState":{"affineTransform":[1,0,0,1,0,0],"masksToBounds":false,"rotation":0,"scale":1,"position":{"pointX":24.28571562256138,"pointY":34.60180652141571},"width":37,"sublayerTransform":[1,0,0,0,0,1,0,0,0,0,1,0,0,0,0,1],"contentsRect":{"y":0,"x":0,"width":1,"height":1},"opacity":1,"edgeAntialiasingMask":0,"height":36,"hidden":true,"anchorPoint":{"pointX":0.5,"pointY":0.5}},"texture":"27A1459428E2114F8A04E93134B69D52"}]}]},"effects":[],"duration":0.9,"type":"buildIn","name":"apple:bc-flip","objectID":"C83C8740-CA88-47B1-854B-000395E53166"}],"automaticPlay":true,"hyperlinks":[],"accessibility":[{"text":"DRAG & DROP YOUR IMAGE -> RIGHT CLICK -> SEND TO BACK","targetRectangle":{"y":521.4022871851921,"x":481.940148516178,"width":957.9840000000004,"height":38}}],"baseLayer":{"animations":[],"initialState":{"affineTransform":[1,0,0,1,0,0],"masksToBounds":true,"rotation":0,"scale":1,"position":{"pointX":960,"pointY":540},"width":1920,"sublayerTransform":[1,0,0,0,0,1,0,0,0,0,1,0,0,0,0,1],"contentsRect":{"y":0,"x":0,"width":1,"height":1},"opacity":1,"edgeAntialiasingMask":0,"height":1080,"hidden":false,"anchorPoint":{"pointX":0.5,"pointY":0.5}},"layers":[{"animations":[],"initialState":{"affineTransform":[1,0,0,1,0,0],"masksToBounds":false,"rotation":0,"scale":1,"position":{"pointX":960,"pointY":540},"width":1920,"sublayerTransform":[1,0,0,0,0,1,0,0,0,0,1,0,0,0,0,1],"contentsRect":{"y":0,"x":0,"width":1,"height":1},"opacity":1,"edgeAntialiasingMask":15,"height":1080,"hidden":false,"anchorPoint":{"pointX":0.5,"pointY":0.5}},"layers":[{"animations":[],"initialState":{"affineTransform":[1,0,0,1,0,0],"masksToBounds":false,"rotation":0,"scale":1,"position":{"pointX":960,"pointY":540},"width":1920,"sublayerTransform":[1,0,0,0,0,1,0,0,0,0,1,0,0,0,0,1],"contentsRect":{"y":0,"x":0,"width":1,"height":1},"opacity":1,"edgeAntialiasingMask":15,"height":1080,"hidden":false,"anchorPoint":{"pointX":0.5,"pointY":0.5}},"layers":[{"animations":[],"layers":[],"initialState":{"affineTransform":[1,0,0,1,0,0],"masksToBounds":false,"rotation":0,"scale":1,"position":{"pointX":960,"pointY":540},"width":1920,"sublayerTransform":[1,0,0,0,0,1,0,0,0,0,1,0,0,0,0,1],"contentsRect":{"y":0,"x":0,"width":1,"height":1},"opacity":1,"edgeAntialiasingMask":0,"height":1080,"hidden":false,"anchorPoint":{"pointX":0.5,"pointY":0.5}},"texture":"0625B09B9D2280932346BEB487E34EC5"}]}]},{"animations":[],"initialState":{"affineTransform":[1,0,0,1,0,0],"masksToBounds":false,"rotation":0,"scale":1,"position":{"pointX":960,"pointY":540},"width":1920,"sublayerTransform":[1,0,0,0,0,1,0,0,0,0,1,0,0,0,0,1],"contentsRect":{"y":0,"x":0,"width":1,"height":1},"opacity":1,"edgeAntialiasingMask":15,"height":1080,"hidden":false,"anchorPoint":{"pointX":0.5,"pointY":0.5}},"layers":[{"animations":[],"initialState":{"affineTransform":[1,0,0,1,0,0],"masksToBounds":false,"rotation":0,"scale":1,"position":{"pointX":959.9999862909317,"pointY":539.9999612569809},"width":1920.500732421875,"sublayerTransform":[1,0,0,0,0,1,0,0,0,0,1,0,0,0,0,1],"contentsRect":{"y":0,"x":0,"width":1,"height":1},"opacity":0.8500000238418579,"edgeAntialiasingMask":15,"height":1083.363525390625,"hidden":false,"anchorPoint":{"pointX":0.5,"pointY":0.5}},"objectID":"BCC952BC-8D61-49CB-BF0A-80C38D5FE59B","layers":[{"animations":[],"layers":[],"initialState":{"affineTransform":[1,0,0,1,0,0],"masksToBounds":false,"rotation":0,"scale":1,"position":{"pointX":960.2503799200058,"pointY":541.6818014383316},"width":1924,"sublayerTransform":[1,0,0,0,0,1,0,0,0,0,1,0,0,0,0,1],"contentsRect":{"y":0,"x":0,"width":1,"height":1},"opacity":1,"edgeAntialiasingMask":0,"height":1086,"hidden":false,"anchorPoint":{"pointX":0.5,"pointY":0.5}},"texture":"E8E583B01A0E2BC12C84C0EBFCE59203"}]}]},{"animations":[],"initialState":{"affineTransform":[1,0,0,1,0,0],"masksToBounds":false,"rotation":0,"scale":1,"position":{"pointX":960,"pointY":540},"width":1920,"sublayerTransform":[1,0,0,0,0,1,0,0,0,0,1,0,0,0,0,1],"contentsRect":{"y":0,"x":0,"width":1,"height":1},"opacity":1,"edgeAntialiasingMask":15,"height":1080,"hidden":false,"anchorPoint":{"pointX":0.5,"pointY":0.5}},"layers":[{"animations":[],"initialState":{"affineTransform":[1,0,0,1,0,0],"masksToBounds":false,"rotation":0,"scale":1,"position":{"pointX":959.9999923706055,"pointY":566.4665451049805},"width":509,"sublayerTransform":[1,0,0,0,0,1,0,0,0,0,1,0,0,0,0,1],"contentsRect":{"y":0,"x":0,"width":1,"height":1},"opacity":1,"edgeAntialiasingMask":15,"height":559,"hidden":false,"anchorPoint":{"pointX":0.5,"pointY":0.5}},"objectID":"36744CC5-8A06-40CA-9654-ED4CA37E5193","layers":[{"animations":[],"layers":[],"initialState":{"affineTransform":[1,0,0,1,0,0],"masksToBounds":false,"rotation":0,"scale":1,"position":{"pointX":254.0000076293945,"pointY":262.5334548950195},"width":421,"sublayerTransform":[1,0,0,0,0,1,0,0,0,0,1,0,0,0,0,1],"contentsRect":{"y":0,"x":0,"width":1,"height":1},"opacity":1,"edgeAntialiasingMask":0,"height":391,"hidden":true,"anchorPoint":{"pointX":0.5,"pointY":0.5}},"texture":"C7B5ACFCFF92ABC36D7C749C7A2B6515"}]}]},{"animations":[],"initialState":{"affineTransform":[1,0,0,1,0,0],"masksToBounds":false,"rotation":0,"scale":1,"position":{"pointX":960,"pointY":540},"width":1920,"sublayerTransform":[1,0,0,0,0,1,0,0,0,0,1,0,0,0,0,1],"contentsRect":{"y":0,"x":0,"width":1,"height":1},"opacity":1,"edgeAntialiasingMask":15,"height":1080,"hidden":false,"anchorPoint":{"pointX":0.5,"pointY":0.5}},"layers":[{"animations":[],"initialState":{"affineTransform":[1,0,0,1,0,0],"masksToBounds":false,"rotation":0,"scale":1,"position":{"pointX":959.999999480588,"pointY":1024.898193478584},"width":47.57143020629883,"sublayerTransform":[1,0,0,0,0,1,0,0,0,0,1,0,0,0,0,1],"contentsRect":{"y":0,"x":0,"width":1,"height":1},"opacity":1,"edgeAntialiasingMask":15,"height":69,"hidden":false,"anchorPoint":{"pointX":0.5,"pointY":0.5}},"objectID":"C83C8740-CA88-47B1-854B-000395E53166","layers":[{"animations":[],"layers":[],"initialState":{"affineTransform":[1,0,0,1,0,0],"masksToBounds":false,"rotation":0,"scale":1,"position":{"pointX":24.28571562256138,"pointY":34.60180652141571},"width":37,"sublayerTransform":[1,0,0,0,0,1,0,0,0,0,1,0,0,0,0,1],"contentsRect":{"y":0,"x":0,"width":1,"height":1},"opacity":1,"edgeAntialiasingMask":0,"height":36,"hidden":true,"anchorPoint":{"pointX":0.5,"pointY":0.5}},"texture":"27A1459428E2114F8A04E93134B69D52"}]}]},{"animations":[],"initialState":{"affineTransform":[1,0,0,1,0,0],"masksToBounds":false,"rotation":0,"scale":1,"position":{"pointX":960,"pointY":540},"width":1920,"sublayerTransform":[1,0,0,0,0,1,0,0,0,0,1,0,0,0,0,1],"contentsRect":{"y":0,"x":0,"width":1,"height":1},"opacity":1,"edgeAntialiasingMask":15,"height":1080,"hidden":false,"anchorPoint":{"pointX":0.5,"pointY":0.5}},"layers":[{"animations":[],"initialState":{"affineTransform":[1,0,0,1,0,0],"masksToBounds":false,"rotation":0,"scale":1,"position":{"pointX":959.9999933242798,"pointY":138.102383852005},"width":881.7304612733424,"sublayerTransform":[1,0,0,0,0,1,0,0,0,0,1,0,0,0,0,1],"contentsRect":{"y":0,"x":0,"width":1,"height":1},"opacity":1,"edgeAntialiasingMask":15,"height":109.0000025267909,"hidden":false,"anchorPoint":{"pointX":0.5,"pointY":0.5}},"objectID":"BDFF1EE7-2C52-439F-AE45-28420255D6E5","layers":[{"animations":[],"layers":[],"initialState":{"affineTransform":[1,0,0,1,0,0],"masksToBounds":false,"rotation":0,"scale":1,"position":{"pointX":439.8652373123914,"pointY":55.39761741139046},"width":868,"sublayerTransform":[1,0,0,0,0,1,0,0,0,0,1,0,0,0,0,1],"contentsRect":{"y":0,"x":0,"width":1,"height":1},"opacity":1,"edgeAntialiasingMask":0,"height":68,"hidden":true,"anchorPoint":{"pointX":0.5,"pointY":0.5}},"texture":"C02892334FA92342460F800E19D89680"}]}]},{"animations":[],"initialState":{"affineTransform":[1,0,0,1,0,0],"masksToBounds":false,"rotation":0,"scale":1,"position":{"pointX":960,"pointY":540},"width":1920,"sublayerTransform":[1,0,0,0,0,1,0,0,0,0,1,0,0,0,0,1],"contentsRect":{"y":0,"x":0,"width":1,"height":1},"opacity":1,"edgeAntialiasingMask":15,"height":1080,"hidden":false,"anchorPoint":{"pointX":0.5,"pointY":0.5}},"layers":[{"animations":[],"initialState":{"affineTransform":[1,0,0,1,0,0],"masksToBounds":false,"rotation":0,"scale":1,"position":{"pointX":960,"pointY":220.1779934167862},"width":982.9769897460938,"sublayerTransform":[1,0,0,0,0,1,0,0,0,0,1,0,0,0,0,1],"contentsRect":{"y":0,"x":0,"width":1,"height":1},"opacity":1,"edgeAntialiasingMask":15,"height":44.00000047683716,"hidden":false,"anchorPoint":{"pointX":0.5,"pointY":0.5}},"objectID":"94CC132C-DEC5-4D1A-882C-F54DBE7A5475","layers":[{"animations":[],"layers":[],"initialState":{"affineTransform":[1,0,0,1,0,0],"masksToBounds":false,"rotation":0,"scale":1,"position":{"pointX":491.4884948730469,"pointY":25.82200682163239},"width":820,"sublayerTransform":[1,0,0,0,0,1,0,0,0,0,1,0,0,0,0,1],"contentsRect":{"y":0,"x":0,"width":1,"height":1},"opacity":1,"edgeAntialiasingMask":0,"height":32,"hidden":true,"anchorPoint":{"pointX":0.5,"pointY":0.5}},"texture":"B5B667008212B1F34D2070F84C2B1478"}]}]},{"animations":[],"initialState":{"affineTransform":[1,0,0,1,0,0],"masksToBounds":false,"rotation":0,"scale":1,"position":{"pointX":960,"pointY":540},"width":1920,"sublayerTransform":[1,0,0,0,0,1,0,0,0,0,1,0,0,0,0,1],"contentsRect":{"y":0,"x":0,"width":1,"height":1},"opacity":1,"edgeAntialiasingMask":15,"height":1080,"hidden":false,"anchorPoint":{"pointX":0.5,"pointY":0.5}},"layers":[{"animations":[],"initialState":{"affineTransform":[1,0,0,1,0,0],"masksToBounds":false,"rotation":0,"scale":1,"position":{"pointX":960.9321485161781,"pointY":540.0000044703484},"width":1920.500732421875,"sublayerTransform":[1,0,0,0,0,1,0,0,0,0,1,0,0,0,0,1],"contentsRect":{"y":0,"x":0,"width":1,"height":1},"opacity":1,"edgeAntialiasingMask":15,"height":1079.195434570312,"hidden":false,"anchorPoint":{"pointX":0.5,"pointY":0.5}},"objectID":"A2C869A0-4B30-4AEF-8647-AA0A8EF14723","layers":[{"animations":[],"layers":[],"initialState":{"affineTransform":[1,0,0,1,0,0],"masksToBounds":false,"rotation":0,"scale":1,"position":{"pointX":960.3182176947594,"pointY":539.5977128148079},"width":1924,"sublayerTransform":[1,0,0,0,0,1,0,0,0,0,1,0,0,0,0,1],"contentsRect":{"y":0,"x":0,"width":1,"height":1},"opacity":1,"edgeAntialiasingMask":0,"height":1082,"hidden":false,"anchorPoint":{"pointX":0.5,"pointY":0.5}},"texture":"C432C237D75414711234682F59B0DA1C"}]}]}]}},{"effects":[{"beginTime":0,"baseLayer":{"animations":[],"initialState":{"affineTransform":[1,0,0,1,0,0],"masksToBounds":true,"rotation":0,"scale":1,"position":{"pointX":960,"pointY":540},"width":1920,"sublayerTransform":[1,0,0,0,0,1,0,0,0,0,1,0,0,0,0,1],"contentsRect":{"y":0,"x":0,"width":1,"height":1},"opacity":1,"edgeAntialiasingMask":0,"height":1080,"hidden":false,"anchorPoint":{"pointX":0.5,"pointY":0.5}},"objectID":"0","layers":[{"animations":[],"initialState":{"affineTransform":[1,0,0,1,0,0],"masksToBounds":false,"rotation":0,"scale":1,"position":{"pointX":960,"pointY":540},"width":1920,"sublayerTransform":[1,0,0,0,0,1,0,0,0,0,1,-0.0003500791246677598,0,0,0,1],"contentsRect":{"y":0,"x":0,"width":1,"height":1},"opacity":1,"edgeAntialiasingMask":15,"height":1080,"hidden":false,"anchorPoint":{"pointX":0.5,"pointY":0.5}},"layers":[{"animations":[{"repeatCount":0,"timingControlPoint2y":0.9959721565246582,"from":{"pointX":960,"pointY":1620},"timingFunction":"custom","timingControlPoint1x":0.4970587193965912,"property":"position","fillMode":"both","duration":1,"beginTime":0,"timingControlPoint2x":0.4981173276901245,"timingControlPoint1y":0,"to":{"pointX":960,"pointY":540}}],"layers":[],"initialState":{"affineTransform":[1,0,0,1,0,0],"masksToBounds":false,"rotation":0,"scale":1,"position":{"pointX":960,"pointY":540},"width":1920,"sublayerTransform":[1,0,0,0,0,1,0,0,0,0,1,0,0,0,0,1],"contentsRect":{"y":0,"x":0,"width":1,"height":1},"opacity":1,"edgeAntialiasingMask":0,"height":1080,"hidden":false,"anchorPoint":{"pointX":0.5,"pointY":0.5}},"texture":"4DEFF49A7D65120150224652EBA0FF43"},{"animations":[{"repeatCount":0,"timingControlPoint2y":0.9959721565246582,"from":{"pointX":960,"pointY":540},"timingFunction":"custom","timingControlPoint1x":0.4970587193965912,"property":"position","fillMode":"both","duration":1,"beginTime":0,"timingControlPoint2x":0.4981173276901245,"timingControlPoint1y":0,"to":{"pointX":960,"pointY":-540}}],"layers":[],"initialState":{"affineTransform":[1,0,0,1,0,0],"masksToBounds":false,"rotation":0,"scale":1,"position":{"pointX":960,"pointY":540},"width":1920,"sublayerTransform":[1,0,0,0,0,1,0,0,0,0,1,0,0,0,0,1],"contentsRect":{"y":0,"x":0,"width":1,"height":1},"opacity":1,"edgeAntialiasingMask":0,"height":1080,"hidden":false,"anchorPoint":{"pointX":0.5,"pointY":0.5}},"texture":"9FD2022F37B1D3211486583890BCABA4"}]}]},"effects":[],"duration":1,"type":"transition","name":"apple:push","objectID":"0"}],"automaticPlay":false,"hyperlinks":[],"accessibility":[{"text":"Little subtitle here like lorem ipsum dolor sit amet lorem ipsum","targetRectangle":{"y":202.1779931783676,"x":549.84375,"width":820.3125,"height":36}},{"text":"b","targetRectangle":{"y":309.9665451049805,"x":709.9999923706055,"width":500,"height":514}},{"text":"","targetRectangle":{"y":995.3981934785843,"x":940.7142843774386,"width":38.57142857142856,"height":60}},{"text":"DRAG & DROP YOUR IMAGE -> RIGHT CLICK -> SEND TO BACK","targetRectangle":{"y":521.4022871851921,"x":481.940148516178,"width":957.9840000000004,"height":38}},{"text":"OUR WORKS ROCKS!","targetRectangle":{"y":87.60238258860954,"x":523.6347626876086,"width":872.73046875,"height":101}}],"baseLayer":{"animations":[],"initialState":{"affineTransform":[1,0,0,1,0,0],"masksToBounds":true,"rotation":0,"scale":1,"position":{"pointX":960,"pointY":540},"width":1920,"sublayerTransform":[1,0,0,0,0,1,0,0,0,0,1,0,0,0,0,1],"contentsRect":{"y":0,"x":0,"width":1,"height":1},"opacity":1,"edgeAntialiasingMask":0,"height":1080,"hidden":false,"anchorPoint":{"pointX":0.5,"pointY":0.5}},"objectID":"0","layers":[{"animations":[],"initialState":{"affineTransform":[1,0,0,1,0,0],"masksToBounds":false,"rotation":0,"scale":1,"position":{"pointX":960,"pointY":540},"width":1920,"sublayerTransform":[1,0,0,0,0,1,0,0,0,0,1,-0.0003500791246677598,0,0,0,1],"contentsRect":{"y":0,"x":0,"width":1,"height":1},"opacity":1,"edgeAntialiasingMask":15,"height":1080,"hidden":false,"anchorPoint":{"pointX":0.5,"pointY":0.5}},"layers":[{"animations":[],"layers":[],"initialState":{"affineTransform":[1,0,0,1,0,0],"masksToBounds":false,"rotation":0,"scale":1,"position":{"pointX":960,"pointY":540},"width":1920,"sublayerTransform":[1,0,0,0,0,1,0,0,0,0,1,0,0,0,0,1],"contentsRect":{"y":0,"x":0,"width":1,"height":1},"opacity":1,"edgeAntialiasingMask":0,"height":1080,"hidden":false,"anchorPoint":{"pointX":0.5,"pointY":0.5}},"texture":"9FD2022F37B1D3211486583890BCABA4"}]}]}}]}